<?xml version="1.0" encoding="UTF-8" ?>
<class name="CreatureGodot" inherits="Node2D" xmlns:xsi="http://www.w3.org/2001/XMLSchema-instance" xsi:noNamespaceSchemaLocation="../class.xsd">
	<brief_description>
	</brief_description>
	<description>
	</description>
	<tutorials>
	</tutorials>
	<methods>
		<method name="add_skinswap">
			<return type="void" />
			<argument index="0" name="name_in" type="String" />
			<argument index="1" name="custom_swap" type="PoolStringArray" />
			<description>
			</description>
		</method>
		<method name="blend_to_animation">
			<return type="bool" />
			<argument index="0" name="animation_name" type="String" />
			<argument index="1" name="blend_delta" type="float" />
			<description>
			</description>
		</method>
		<method name="clear_custom_region_color">
			<return type="void" />
			<argument index="0" name="region_name" type="String" />
			<description>
			</description>
		</method>
		<method name="disable_skinswap_or_order">
			<return type="void" />
			<description>
			</description>
		</method>
		<method name="enable_layerorder">
			<return type="void" />
			<description>
			</description>
		</method>
		<method name="enable_skinswap">
			<return type="void" />
			<description>
			</description>
		</method>
		<method name="get_anim_clips" qualifiers="const">
			<return type="PoolStringArray" />
			<description>
			</description>
		</method>
		<method name="get_bone_pos">
			<return type="Vector2" />
			<argument index="0" name="bone_name" type="String" />
			<argument index="1" name="slide_factor" type="float" />
			<description>
			</description>
		</method>
		<method name="get_morph_targets_active" qualifiers="const">
			<return type="bool" />
			<description>
			</description>
		</method>
		<method name="load_json">
			<return type="bool" />
			<argument index="0" name="_arg0" type="String" />
			<description>
			</description>
		</method>
		<method name="make_point_cache">
			<return type="void" />
			<argument index="0" name="animation_name_in" type="String" />
			<argument index="1" name="gap_step" type="int" />
			<description>
			</description>
		</method>
		<method name="remove_active_item_swap">
			<return type="void" />
			<argument index="0" name="region_name" type="String" />
			<description>
			</description>
		</method>
		<method name="remove_skinswap">
			<return type="void" />
			<argument index="0" name="name_in" type="String" />
			<description>
			</description>
		</method>
		<method name="set_active_item_swap">
			<return type="void" />
			<argument index="0" name="region_name" type="String" />
			<argument index="1" name="swap_idx" type="int" />
			<description>
			</description>
		</method>
		<method name="set_anchor_points_active">
			<return type="void" />
			<argument index="0" name="flag_in" type="bool" />
			<description>
			</description>
		</method>
		<method name="set_custom_region_color">
			<return type="void" />
			<argument index="0" name="region_name" type="String" />
			<argument index="1" name="color_in" type="Color" />
			<description>
			</description>
		</method>
		<method name="set_morph_targets_active">
			<return type="void" />
			<argument index="0" name="flag_in" type="bool" />
			<description>
			</description>
		</method>
		<method name="set_morph_targets_pt">
			<return type="void" />
			<argument index="0" name="pt_in" type="Vector2" />
			<argument index="1" name="base_pt" type="Vector2" />
			<argument index="2" name="radius" type="float" />
			<description>
			</description>
		</method>
		<method name="set_should_loop">
			<return type="void" />
			<argument index="0" name="flag_in" type="bool" />
			<description>
			</description>
		</method>
		<method name="set_skinswap_name">
			<return type="void" />
			<argument index="0" name="name_in" type="String" />
			<description>
			</description>
		</method>
		<method name="update_animation">
			<return type="void" />
			<argument index="0" name="delta" type="float" />
			<description>
			</description>
		</method>
	</methods>
	<members>
		<member name="anim_frame" type="float" setter="set_anim_frame" getter="get_anim_frame" default="0.0">
		</member>
		<member name="anim_name" type="String" setter="set_anim_name" getter="get_anim_name" default="&quot;&quot;">
		</member>
		<member name="anim_speed" type="float" setter="set_anim_speed" getter="get_anim_speed" default="2.0">
		</member>
		<member name="asset_filename" type="String" setter="set_asset_filename" getter="get_asset_filename" default="&quot;&quot;">
		</member>
		<member name="color" type="Color" setter="set_color" getter="get_color" default="Color( 1, 1, 1, 1 )">
		</member>
		<member name="metadata_filename" type="String" setter="set_metadata_filename" getter="get_metadata_filename" default="&quot;&quot;">
		</member>
		<member name="mirror_y" type="bool" setter="set_mirror_y" getter="get_mirror_y" default="false">
		</member>
		<member name="offset" type="Vector2" setter="set_offset" getter="get_offset" default="Vector2( 0, 0 )">
		</member>
		<member name="texture/texture" type="Texture" setter="set_texture" getter="get_texture">
		</member>
	</members>
	<constants>
	</constants>
</class>
